graphunzip/__init__.py
graphunzip/_version.py
graphunzip/analyse_HiC.py
graphunzip/analyse_coverage_HiC.py
graphunzip/arg_helpers.py
graphunzip/check_phasing.py
graphunzip/clean_graph.py
graphunzip/determine_multiplicity.py
graphunzip/docopt.py
graphunzip/finish_untangling.py
graphunzip/graphunzip.py
graphunzip/input_output.py
graphunzip/interaction_between_contigs.py
graphunzip/run_submodules.py
graphunzip/segment.py
graphunzip/solve_ambiguities.py
graphunzip/solve_with_HiC.py
graphunzip/solve_with_long_reads.py
graphunzip/tests.py
graphunzip/transform_gfa.py
graphunzip/trash.py
graphunzip/pybam/LICENSE
graphunzip/pybam/README.md
graphunzip/pybam/pybam.py
GraphUnzip-3.0.0.dist-info/LICENSE
GraphUnzip-3.0.0.dist-info/METADATA
GraphUnzip-3.0.0.dist-info/WHEEL
GraphUnzip-3.0.0.dist-info/entry_points.txt
GraphUnzip-3.0.0.dist-info/top_level.txt
GraphUnzip-3.0.0.dist-info/RECORD
