Metadata-Version: 2.1
Name: GraphUnzip
Version: 3.0.0
Summary: Unzips an assembly graph using Hi-C data and/or long reads and/or linked reads.
Author-email: Roland Faure <roland.faure@irisa.fr>, Nadège Guiglielmoni <nadege.guiglielmoni@ulb.be>, Jean-François Flot <jean-francois.flot@ulb.be>
License: GPL
Project-URL: homepage, https://github.com/nadegeguiglielmoni/GraphUnzip
Project-URL: documentation, https://github.com/nadegeguiglielmoni/GraphUnzip
Project-URL: repository, https://github.com/nadegeguiglielmoni/GraphUnzip
Classifier: Programming Language :: Python :: 3
Classifier: Intended Audience :: Science/Research
Classifier: Topic :: Scientific/Engineering :: Bio-Informatics
Classifier: License :: OSI Approved :: GNU General Public License (GPL)
Requires-Python: >=3.7
License-File: LICENSE
Requires-Dist: numpy
Requires-Dist: scipy
Requires-Dist: pysam
Requires-Dist: setuptools-scm
Requires-Dist: matplotlib
Requires-Dist: pandas
Requires-Dist: biopython
